hpyre/__init__.py
hpyre/hpyre.py
hpyre-0.1.0.dist-info/METADATA
hpyre-0.1.0.dist-info/WHEEL
hpyre-0.1.0.dist-info/top_level.txt
hpyre-0.1.0.dist-info/RECORD
