Metadata-Version: 2.1
Name: hpyre
Version: 0.1.0
Summary: Electroporation data analysis
Home-page: UNKNOWN
Author: Pedro Paulo
Author-email: <ppaulo437@gmail.com>
License: UNKNOWN
Keywords: python,electroporation,fft
Platform: UNKNOWN
Classifier: Development Status :: 1 - Planning
Classifier: Intended Audience :: Developers
Classifier: Programming Language :: Python :: 3
Classifier: Operating System :: Unix
Classifier: Operating System :: MacOS :: MacOS X
Classifier: Operating System :: Microsoft :: Windows
Requires-Dist: numpy
Requires-Dist: pandas
Requires-Dist: scipy
Requires-Dist: matplotlib
Requires-Dist: tk
Requires-Dist: lecroyscope
Requires-Dist: isfreader
